tidye/__init__.py
tidye/__main__.py
tidye/model.py
tidye/simulation.py
tidye-0.1.4.dist-info/LICENSE
tidye-0.1.4.dist-info/METADATA
tidye-0.1.4.dist-info/WHEEL
tidye-0.1.4.dist-info/entry_points.txt
tidye-0.1.4.dist-info/RECORD
