Metadata-Version: 2.1
Name: tidye
Version: 0.1.4
Summary: Tidal simulation with multiple moons (for Emily)
Author: William Dye
Requires-Python: >=3.9,<4.0
Classifier: Programming Language :: Python :: 3
Classifier: Programming Language :: Python :: 3.9
Classifier: Programming Language :: Python :: 3.10
Classifier: Programming Language :: Python :: 3.11
Requires-Dist: matplotlib (==3.9)
Requires-Dist: numpy (==2.0)
